stdimage/__init__.py
stdimage/models.py
stdimage/utils.py
stdimage/validators.py
stdimage/locale/de/LC_MESSAGES/django.mo
stdimage/locale/de/LC_MESSAGES/django.po
stdimage/locale/fr/LC_MESSAGES/django.mo
stdimage/locale/fr/LC_MESSAGES/django.po
stdimage/locale/sr/LC_MESSAGES/django.mo
stdimage/locale/sr/LC_MESSAGES/django.po
stdimage/locale/sr_Latn/LC_MESSAGES/django.mo
stdimage/locale/sr_Latn/LC_MESSAGES/django.po
stdimage/management/__init__.py
stdimage/management/commands/__init__.py
stdimage/management/commands/rendervariations.py
django_stdimage-6.0.2.dist-info/LICENSE
django_stdimage-6.0.2.dist-info/METADATA
django_stdimage-6.0.2.dist-info/WHEEL
django_stdimage-6.0.2.dist-info/top_level.txt
django_stdimage-6.0.2.dist-info/RECORD
