Metadata-Version: 2.1
Name: django-stdimage
Version: 6.0.2
Summary: Django Standarized Image Field
Home-page: https://github.com/codingjoe/django-stdimage
Author: Johannes Hoppe
Author-email: info@johanneshoppe.com
License: MIT
Classifier: Development Status :: 7 - Inactive
Classifier: Environment :: Web Environment
Classifier: Framework :: Django
Classifier: Topic :: Multimedia :: Graphics :: Graphics Conversion
Classifier: Intended Audience :: Developers
Classifier: License :: OSI Approved :: MIT License
Classifier: Operating System :: OS Independent
Classifier: Programming Language :: Python
Classifier: Topic :: Software Development
Classifier: Programming Language :: Python :: 3
Classifier: Programming Language :: Python :: 3 :: Only
Classifier: Programming Language :: Python :: 3.8
Classifier: Programming Language :: Python :: 3.9
Classifier: Programming Language :: Python :: 3.10
Classifier: Framework :: Django
Classifier: Framework :: Django :: 3.2
Classifier: Framework :: Django :: 4.0
License-File: LICENSE
Requires-Dist: Django>=2.2
Requires-Dist: pillow>=2.5
Provides-Extra: test
Requires-Dist: pytest; extra == "test"
Requires-Dist: pytest-cov; extra == "test"
Requires-Dist: pytest-django; extra == "test"
Provides-Extra: progressbar
Requires-Dist: progressbar2>=3.0.0; extra == "progressbar"
